CHANGES.txt
LICENSE.txt
MANIFEST.in
README.rst
setup.py
django_echo.egg-info/PKG-INFO
django_echo.egg-info/SOURCES.txt
django_echo.egg-info/dependency_links.txt
django_echo.egg-info/top_level.txt
echo/__init__.py
echo/request.py
echo/response.py
echo/skill.py
echo/tests/__init__.py
echo/tests/test_request.py
echo/tests/test_response.py
echo/tests/test_skill.py