Metadata-Version: 1.1
Name: django-echo
Version: 0.1.2
Summary: Library for creating skills for the Amazon Echo
Home-page: https://github.com/bunchesofdonald/django-echo
Author: Chris Pickett
Author-email: chris.pickett@gmail.com
License: MIT
Platform: UNKNOWN
Classifier: Development Status :: 3 - Alpha
Classifier: Environment :: Web Environment
Classifier: Intended Audience :: Developers
Classifier: License :: OSI Approved :: MIT License
Classifier: Operating System :: OS Independent
Classifier: Programming Language :: Python
Classifier: Programming Language :: Python :: 2
Classifier: Programming Language :: Python :: 3
Classifier: Framework :: Django
Classifier: Natural Language :: English
